{
  "packageId": "ai.drivex.app",
  "host": "auto-guardian-kappa.vercel.app",
  "name": "AI DriveX",
  "launcherName": "AI DriveX",
  "display": "standalone",
  "themeColor": "#020617",
  "themeColorDark": "#020617",
  "navigationColor": "#020617",
  "navigationColorDark": "#020617",
  "navigationDividerColor": "#020617",
  "navigationDividerColorDark": "#020617",
  "backgroundColor": "#020617",
  "enableNotifications": true,
  "startUrl": "/?source=twa",
  "iconUrl": "https://auto-guardian-kappa.vercel.app/icons/icon-512.png",
  "maskableIconUrl": "https://auto-guardian-kappa.vercel.app/icons/icon-512-maskable.png",
  "monochromeIconUrl": "https://auto-guardian-kappa.vercel.app/icons/icon-512.png",
  "shortcuts": [
    {
      "name": "Diagnostics",
      "shortName": "Diag",
      "url": "/diagnostics",
      "chosenIconUrl": "https://auto-guardian-kappa.vercel.app/icons/icon-192.png"
    },
    {
      "name": "Wallet",
      "shortName": "Wallet",
      "url": "/wallet",
      "chosenIconUrl": "https://auto-guardian-kappa.vercel.app/icons/icon-192.png"
    },
    {
      "name": "Emergency",
      "shortName": "SOS",
      "url": "/emergency",
      "chosenIconUrl": "https://auto-guardian-kappa.vercel.app/icons/icon-192.png"
    }
  ],
  "generatorApp": "Bubblewrap-CLI",
  "webManifestUrl": "https://auto-guardian-kappa.vercel.app/manifest.webmanifest",
  "fallbackType": "customtabs",
  "features": {
    "locationDelegation": { "enabled": false },
    "playBilling": { "enabled": false }
  },
  "alphaDependencies": { "enabled": false },
  "enableSiteSettingsShortcut": true,
  "isChromeOSOnly": false,
  "isMetaQuest": false,
  "fullScopeUrl": "https://auto-guardian-kappa.vercel.app/",
  "minSdkVersion": 21,
  "orientation": "portrait",
  "fingerprints": [],
  "additionalTrustedOrigins": [],
  "retainedBundles": [],
  "signingKey": {
    "path": "./android.keystore",
    "alias": "android"
  },
  "appVersionName": "1.0.0",
  "appVersionCode": 1,
  "splashScreenFadeOutDuration": 300
}
